{
    "alsoKnownAs": [
        "Juggler"
    ],
    "appleName": "Person Juggling",
    "code": "🤹",
    "codepointsHex": [
        "U+1F939"
    ],
    "components": [
        {
            "alsoKnownAs": [
                "Juggler"
            ],
            "appleName": "Person Juggling",
            "code": "🤹",
            "codepointsHex": [
                "U+1F939"
            ],
            "currentCldrName": "Person Juggling",
            "description": "<p>A person juggling between three and five colored balls. The person shown in this emoji wears a hat on most major platforms.</p>\r\n\r\n<p>Early <a href=\"/twitter/twemoji-2.1/person-juggling/\">Twitter</a> and <a href=\"/facebook/2.0/person-juggling/\">Facebook</a> designs previously displayed this emoji as a pair of disembodied hands juggling three&nbsp;colored balls.</p>",
            "id": "1380",
            "modifiers": true,
            "slug": "person-juggling",
            "shortcodes": [
                {
                    "code": ":person_juggling:",
                    "vendor": {
                        "slug": "shortcodes",
                        "title": "Emojipedia"
                    }
                },
                {
                    "code": ":juggling_person:",
                    "vendor": {
                        "slug": "github",
                        "title": "GitHub"
                    }
                },
                {
                    "code": ":juggling:",
                    "vendor": {
                        "slug": "slack",
                        "title": "Slack"
                    }
                },
                {
                    "code": ":person_juggling:",
                    "vendor": {
                        "slug": "discord",
                        "title": "Discord"
                    }
                },
                {
                    "code": ":juggling:",
                    "vendor": {
                        "slug": "discord",
                        "title": "Discord"
                    }
                },
                {
                    "code": ":juggler:",
                    "vendor": {
                        "slug": "discord",
                        "title": "Discord"
                    }
                }
            ],
            "title": "Juggling"
        }
    ],
    "currentCldrName": "Person Juggling",
    "description": "<p>A person juggling between three and five colored balls. The person shown in this emoji wears a hat on most major platforms.</p>\r\n\r\n<p>Early <a href=\"/twitter/twemoji-2.1/person-juggling/\">Twitter</a> and <a href=\"/facebook/2.0/person-juggling/\">Facebook</a> designs previously displayed this emoji as a pair of disembodied hands juggling three&nbsp;colored balls.</p>",
    "emojiVersion": {
        "date": 1464825600,
        "name": "3.0",
        "slug": "emoji-3.0",
        "status": 0
    },
    "id": "1380",
    "modifiers": true,
    "shortcodes": [
        {
            "code": ":person_juggling:",
            "vendor": {
                "slug": "shortcodes",
                "title": "Emojipedia"
            },
            "source": "cldr"
        },
        {
            "code": ":juggling_person:",
            "vendor": {
                "slug": "github",
                "title": "GitHub"
            },
            "source": "github"
        },
        {
            "code": ":juggling:",
            "vendor": {
                "slug": "slack",
                "title": "Slack"
            },
            "source": "slack"
        },
        {
            "code": ":person_juggling:",
            "vendor": {
                "slug": "discord",
                "title": "Discord"
            },
            "source": "discord"
        },
        {
            "code": ":juggling:",
            "vendor": {
                "slug": "discord",
                "title": "Discord"
            },
            "source": "discord"
        },
        {
            "code": ":juggler:",
            "vendor": {
                "slug": "discord",
                "title": "Discord"
            },
            "source": "discord"
        }
    ],
    "slug": "person-juggling",
    "title": "Juggling",
    "type": "SINGLE",
    "version": {
        "date": 1466467200,
        "description": "<p>The Unicode Consortium accepted the following emoji 72 emojis&nbsp;for Unicode 9.0. This update&nbsp;was released&nbsp;on June 21, 2016. Most vendors added support for this update within the 2016 calendar year.&nbsp;<a href=\"http://blog.emojipedia.org/unicode-9-0-released-with-72-new-emojis/\">Sample images and more about Unicode 9.0</a>.</p>\r\n\r\n<p><a href=\"/emoji-4.0/\">Emoji 4.0</a> was published in late 2016, which added additional emoji professions.</p>\r\n\r\n<h2>New in Unicode 9</h2>",
        "name": "9.0",
        "slug": "unicode-9.0",
        "status": 0
    }
}