{
    "alsoKnownAs": [
        "Skiing",
        "Skis"
    ],
    "appleName": "Skis",
    "code": "🎿",
    "codepointsHex": [
        "U+1F3BF"
    ],
    "components": [
        {
            "alsoKnownAs": [
                "Skiing",
                "Skis"
            ],
            "appleName": "Skis",
            "code": "🎿",
            "codepointsHex": [
                "U+1F3BF"
            ],
            "currentCldrName": "Skis",
            "description": "<p>A pair of skis which are shown on some platforms alongside ski poles and/or ski boots. The color and design of the skis varies by platform, with some versions also showing the skis moving at speed.</p>\r\n\r\n<p>Distinct from the <a href=\"/skier/\">skier emoji</a> which features a person skiing.</p>",
            "id": "668",
            "slug": "skis",
            "shortcodes": [
                {
                    "code": ":skis:",
                    "vendor": {
                        "slug": "shortcodes",
                        "title": "Emojipedia"
                    }
                },
                {
                    "code": ":ski:",
                    "vendor": {
                        "slug": "github",
                        "title": "GitHub"
                    }
                },
                {
                    "code": ":ski:",
                    "vendor": {
                        "slug": "slack",
                        "title": "Slack"
                    }
                }
            ],
            "title": "Ski and Ski Boot"
        }
    ],
    "currentCldrName": "Skis",
    "description": "<p>A pair of skis which are shown on some platforms alongside ski poles and/or ski boots. The color and design of the skis varies by platform, with some versions also showing the skis moving at speed.</p>\r\n\r\n<p>Distinct from the <a href=\"/skier/\">skier emoji</a> which features a person skiing.</p>",
    "emojiVersion": {
        "date": 1438646400,
        "name": "1.0",
        "slug": "emoji-1.0",
        "status": 0
    },
    "id": "668",
    "shortcodes": [
        {
            "code": ":skis:",
            "vendor": {
                "slug": "shortcodes",
                "title": "Emojipedia"
            },
            "source": "cldr"
        },
        {
            "code": ":ski:",
            "vendor": {
                "slug": "github",
                "title": "GitHub"
            },
            "source": "github"
        },
        {
            "code": ":ski:",
            "vendor": {
                "slug": "slack",
                "title": "Slack"
            },
            "source": "slack"
        }
    ],
    "slug": "skis",
    "title": "Ski and Ski Boot",
    "type": "SINGLE",
    "version": {
        "date": 1286755200,
        "description": "<p>Released in&nbsp;October&nbsp;2010, Unicode 6.0 was the first version of the Unicode Standard to support emoji.</p>\r\n\r\n<p>Some characters in <a href=\"/unicode-5.2/\">prior</a>&nbsp;versions of Unicode were retroactively updated to provide&nbsp;an emoji presentation. This release was the first to introduce new characters for the sole purpose of compatability with emojis being used in Japan.</p>",
        "name": "6.0",
        "slug": "unicode-6.0",
        "status": 0
    }
}