{
    "alsoKnownAs": [
        "Applause",
        "Clap",
        "Clapping",
        "Golf Clap",
        "Round Of Applause"
    ],
    "appleName": "Clapping Hands",
    "code": "👏",
    "codepointsHex": [
        "U+1F44F"
    ],
    "components": [
        {
            "alsoKnownAs": [
                "Applause",
                "Clap",
                "Clapping",
                "Golf Clap",
                "Round Of Applause"
            ],
            "appleName": "Clapping Hands",
            "code": "👏",
            "codepointsHex": [
                "U+1F44F"
            ],
            "currentCldrName": "Clapping Hands",
            "description": "<p>Two hands clapping emoji, which when used multiple times can be used&nbsp;as a round of applause.</p>",
            "id": "138",
            "modifiers": true,
            "slug": "clapping-hands",
            "shortcodes": [
                {
                    "code": ":clapping_hands:",
                    "vendor": {
                        "slug": "shortcodes",
                        "title": "Emojipedia"
                    }
                },
                {
                    "code": ":clap:",
                    "vendor": {
                        "slug": "github",
                        "title": "GitHub"
                    }
                },
                {
                    "code": ":clap:",
                    "vendor": {
                        "slug": "slack",
                        "title": "Slack"
                    }
                },
                {
                    "code": ":clap:",
                    "vendor": {
                        "slug": "discord",
                        "title": "Discord"
                    }
                }
            ],
            "title": "Clapping Hands Sign"
        }
    ],
    "currentCldrName": "Clapping Hands",
    "description": "<p>Two hands clapping emoji, which when used multiple times can be used&nbsp;as a round of applause.</p>",
    "emojiVersion": {
        "date": 1438646400,
        "name": "1.0",
        "slug": "emoji-1.0",
        "status": 0
    },
    "id": "138",
    "modifiers": true,
    "shortcodes": [
        {
            "code": ":clapping_hands:",
            "vendor": {
                "slug": "shortcodes",
                "title": "Emojipedia"
            },
            "source": "cldr"
        },
        {
            "code": ":clap:",
            "vendor": {
                "slug": "github",
                "title": "GitHub"
            },
            "source": "github"
        },
        {
            "code": ":clap:",
            "vendor": {
                "slug": "slack",
                "title": "Slack"
            },
            "source": "slack"
        },
        {
            "code": ":clap:",
            "vendor": {
                "slug": "discord",
                "title": "Discord"
            },
            "source": "discord"
        }
    ],
    "slug": "clapping-hands",
    "title": "Clapping Hands Sign",
    "type": "SINGLE",
    "version": {
        "date": 1286755200,
        "description": "<p>Released in&nbsp;October&nbsp;2010, Unicode 6.0 was the first version of the Unicode Standard to support emoji.</p>\r\n\r\n<p>Some characters in <a href=\"/unicode-5.2/\">prior</a>&nbsp;versions of Unicode were retroactively updated to provide&nbsp;an emoji presentation. This release was the first to introduce new characters for the sole purpose of compatability with emojis being used in Japan.</p>",
        "name": "6.0",
        "slug": "unicode-6.0",
        "status": 0
    }
}